supply_chain_security_nyu/main.py
supply_chain_security_nyu/merkle_proof.py
supply_chain_security_nyu/util.py
supply_chain_security_nyu-2.0.3.dist-info/METADATA
supply_chain_security_nyu-2.0.3.dist-info/WHEEL
supply_chain_security_nyu-2.0.3.dist-info/entry_points.txt
supply_chain_security_nyu-2.0.3.dist-info/licenses/LICENSE.md
supply_chain_security_nyu-2.0.3.dist-info/RECORD
