Metadata-Version: 2.4
Name: supply-chain-security-nyu
Version: 2.0.3
Summary: Supply Chain Security Project Dependencies
License: MIT
License-File: LICENSE.md
Author: vinayakmalik1999
Requires-Python: >=3.9,<4.0
Classifier: License :: OSI Approved :: MIT License
Classifier: Programming Language :: Python :: 3
Classifier: Programming Language :: Python :: 3.9
Classifier: Programming Language :: Python :: 3.10
Classifier: Programming Language :: Python :: 3.11
Classifier: Programming Language :: Python :: 3.12
Classifier: Programming Language :: Python :: 3.13
Classifier: Programming Language :: Python :: 3.14
Requires-Dist: cryptography (==41.0.0)
Requires-Dist: cyclonedx-bom (>=7.2.1,<8.0.0)
Requires-Dist: pre-commit (==4.3.0)
Requires-Dist: requests (==2.32.5)
